{
 "name": "global ghg production",
 "children": [
  {
   "name": "China", "size": 10552,
   "children": [
    {"name": "cluster"},
    {"name": "graph"},
    {"name": "optimization"}
   ]
  },
  {
   "name": "United States", "size": 6550,
   "children": [
    {"name": "Easing", "size": 170},
    {"name": "FunctionSequence", "size": 584},
    {"name": "interpolate"},
    {"name": "ISchedulable", "size": 104},
    {"name": "Parallel", "size": 51},
    {"name": "Pause", "size": 44},
    {"name": "Scheduler", "size": 55},
    {"name": "Sequence", "size": 553},
    {"name": "Transition", "size": 92},
    {"name": "Transitioner", "size": 199},
    {"name": "TransitionEvent", "size": 111},
    {"name": "Tween", "size": 60}
   ]
  },
  {
   "name": "India", "size": 2486,
   "children": [
    {"name": "converters"},
    {"name": "DataField", "size": 175},
    {"name": "DataSchema", "size": 216},
    {"name": "DataSet", "size": 586},
    {"name": "DataSource", "size": 333},
    {"name": "DataTable", "size": 77},
    {"name": "DataUtil", "size": 332}
   ]
  },
  {
   "name": "Russia", "size": 2374,
   "children": [
    {"name": "AggregateExpression", "size": 161},
    {"name": "And", "size": 10},
    {"name": "Arithmetic", "size": 389},
    {"name": "Average", "size": 89},
    {"name": "BinaryExpression", "size": 28},
    {"name": "Comparison", "size": 51},
    {"name": "CompositeExpression", "size": 36},
    {"name": "Count", "size": 78},
    {"name": "DateUtil", "size": 41},
    {"name": "Distinct", "size": 93},
    {"name": "Expression", "size": 51}
   ]
  },
  {
   "name": "Japan", "size": 1307,
   "children": [
    {"name": "IScaleMap", "size": 210},
    {"name": "LinearScale", "size": 131},
    {"name": "LogScale", "size": 315},
    {"name": "OrdinalScale", "size": 37}
   ]
  },
  {
   "name": "Brazil", "size": 1131,
   "children": [
    {"name": "Arrays", "size": 82},
    {"name": "Colors", "size": 10},
    {
     "name": "heap",
     "children": [
      {"name": "FibonacciHeap", "size": 93},
      {"name": "HeapNode", "size": 12}
     ]
    },
    {"name": "IEvaluable", "size": 33},
    {"name": "IPredicate", "size": 38},
    {"name": "IValueProxy", "size": 87},
    {"name": "Maths", "size": 17}
   ]
  },
  {
   "name": "Germany", "size": 882,
   "children": [
    {"name": "IScaleMap", "size": 210},
    {"name": "LinearScale", "size": 131},
    {"name": "LogScale", "size": 31},
    {"name": "OrdinalScale", "size": 37}
   ]
  },
  {
   "name": "Indonesia", "size": 700,
   "children": [
    {"name": "IScaleMap", "size": 210},
    {"name": "LinearScale", "size": 130},
    {"name": "LogScale", "size": 315},
    {"name": "OrdinalScale", "size": 37}
   ]
  },
  {
   "name": "Canada", "size": 650,
   "children": [
    {"name": "IScaleMap", "size": 210},
    {"name": "LinearScale", "size": 131},
    {"name": "LogScale", "size": 31},
    {"name": "OrdinalScale", "size": 37}
   ]
  },
  {
   "name": "Other", "size": 16094,
   "children": [
    {"name": "axis"},
    {"name": "controls"},
    {"name": "events"},
    {"name": "legend"},
    {"name": "Visualization", "size": 16}
   ]
  }
 ]
}
